pysoundtool/__init__.py
pysoundtool/augment.py
pysoundtool/builtin.py
pysoundtool/datasets.py
pysoundtool/dsp.py
pysoundtool/exceptions.py
pysoundtool/feats.py
pysoundtool/files.py
pysoundtool/filters.py
pysoundtool/utils.py
pysoundtool/models/__init__.py
pysoundtool/models/dataprep.py
pysoundtool/models/modelsetup.py
pysoundtool/models/plot.py
pysoundtool/models/template_models.py
pysoundtool_online/models/__init__.py
pysoundtool_online/models/dataprep.py
pysoundtool_online/models/modelsetup.py
pysoundtool_online/models/plot.py
pysoundtool_online/models/template_models.py
soundpy/__init__.py
soundpy/augment.py
soundpy/builtin.py
soundpy/datasets.py
soundpy/dsp.py
soundpy/exceptions.py
soundpy/feats.py
soundpy/files.py
soundpy/filters.py
soundpy/utils.py
soundpy/models/__init__.py
soundpy/models/builtin.py
soundpy/models/dataprep.py
soundpy/models/modelsetup.py
soundpy/models/plot.py
soundpy/models/template_models.py
soundpy-0.1.0a3.dist-info/LICENSE.md
soundpy-0.1.0a3.dist-info/METADATA
soundpy-0.1.0a3.dist-info/WHEEL
soundpy-0.1.0a3.dist-info/top_level.txt
soundpy-0.1.0a3.dist-info/RECORD
