Metadata-Version: 2.1
Name: soundpy
Version: 0.1.0a3
Summary: A research-based framework for exploring sound as well as machine learning in the context of sound.
Home-page: https://github.com/a-n-rose/Python-Sound-Tool
Author: Aislyn Rose
Author-email: rose.aislyn.noelle@gmail.com
License: AGPL-3.0
Platform: UNKNOWN
Classifier: License :: OSI Approved :: GNU Affero General Public License v3
Classifier: Programming Language :: Python :: 3
Classifier: Programming Language :: Python :: 3.6
Classifier: Programming Language :: Python :: 3.8
Requires-Python: >=3.6.9
Requires-Dist: tensorflow (>=2.1.0)
Requires-Dist: numpy
Requires-Dist: scipy
Requires-Dist: scikit-learn
Requires-Dist: librosa
Requires-Dist: python-speech-features
Requires-Dist: matplotlib
Requires-Dist: soundfile
Requires-Dist: numba
Requires-Dist: scikit-image (>=0.17.2)
